kartverkets_api/__init__.py
kartverkets_api/kartverket.py
kartverkets_api-0.1.16.dist-info/METADATA
kartverkets_api-0.1.16.dist-info/WHEEL
kartverkets_api-0.1.16.dist-info/RECORD
