Metadata-Version: 2.3
Name: kartverkets-api
Version: 0.1.16
Summary: Unofficial client for Kartverket's API for property data (Grunnboken and Matrikkelen).
Author: sigvardbratlie
Author-email: sigvard.bratlie@gmail.com
Requires-Python: >=3.11
Classifier: Programming Language :: Python :: 3
Classifier: Programming Language :: Python :: 3.11
Classifier: Programming Language :: Python :: 3.12
Classifier: Programming Language :: Python :: 3.13
Provides-Extra: test
Requires-Dist: aiohttp (>=3.12.15,<4.0.0)
Requires-Dist: aresponses ; extra == "test"
Requires-Dist: numpy (>=2.3.2,<3.0.0)
Requires-Dist: pandas (>=2.3.2,<3.0.0)
Requires-Dist: pytest ; extra == "test"
Requires-Dist: pytest-asyncio ; extra == "test"
Requires-Dist: requests (>=2.32.5,<3.0.0)
Requires-Dist: sibr-api (>=0.3.2,<0.4.0)
Requires-Dist: zeep (>=4.3.1,<5.0.0)
